textcleaner/__init__.py
textcleaner/textcleaner.py
text_cleaner_emagister-2.0.2.dist-info/LICENSE
text_cleaner_emagister-2.0.2.dist-info/METADATA
text_cleaner_emagister-2.0.2.dist-info/WHEEL
text_cleaner_emagister-2.0.2.dist-info/top_level.txt
text_cleaner_emagister-2.0.2.dist-info/RECORD
