Metadata-Version: 2.1
Name: text-cleaner-emagister
Version: 2.0.2
Summary: Tools for cleaning and preprocessing text
Home-page: https://github.com/Emagister/py-text-cleaner.git
Author: Cisco Delgado
Author-email: fdelgado@emagister.com
Requires-Python: >=3.8
License-File: LICENSE
Requires-Dist: beautifulsoup4 (==4.9.3)
Requires-Dist: Unidecode (==1.3.2)
